sroc/__init__.py
sroc/canvas.py
sroc/overlay.py
sroc-0.2.3.dist-info/LICENSE
sroc-0.2.3.dist-info/METADATA
sroc-0.2.3.dist-info/WHEEL
sroc-0.2.3.dist-info/RECORD
