Metadata-Version: 2.3
Name: sroc
Version: 0.2.3
Summary: Straight Rectangles on Canvas
License: GPL-3.0
Author: Giovanni Cascione
Author-email: ing.cascione@gmail.com
Requires-Python: >=3.8,<4.0
Classifier: License :: OSI Approved :: GNU General Public License v3 (GPLv3)
Classifier: Programming Language :: Python :: 3
Classifier: Programming Language :: Python :: 3.8
Classifier: Programming Language :: Python :: 3.9
Classifier: Programming Language :: Python :: 3.10
Classifier: Programming Language :: Python :: 3.11
Classifier: Programming Language :: Python :: 3.12
Classifier: Programming Language :: Python :: 3.13
Requires-Dist: matplotlib (>=3.4.3,<4.0.0)
Requires-Dist: numpy (>=1.21.2,<2.0.0)
Requires-Dist: opencv-python (>=4.5.3,<5.0.0)
Project-URL: Homepage, https://github.com/spleen1981/pySROC
